haystack_integrations/tools/mcp/__init__.py
haystack_integrations/tools/mcp/mcp_tool.py
haystack_integrations/tools/mcp/mcp_toolset.py
haystack_integrations/tools/mcp/py.typed
mcp_haystack-1.2.0.dist-info/METADATA
mcp_haystack-1.2.0.dist-info/WHEEL
mcp_haystack-1.2.0.dist-info/licenses/LICENSE.txt
mcp_haystack-1.2.0.dist-info/RECORD
