Metadata-Version: 2.4
Name: mcp-haystack
Version: 1.2.0
Summary: Haystack integration for Model Context Protocol (MCP)
Project-URL: Documentation, https://github.com/deepset-ai/haystack-core-integrations/tree/main/integrations/mcp#readme
Project-URL: Issues, https://github.com/deepset-ai/haystack-core-integrations/issues
Project-URL: Source, https://github.com/deepset-ai/haystack-core-integrations/tree/main/integrations/mcp
Author-email: deepset GmbH <info@deepset.ai>
License-Expression: Apache-2.0
License-File: LICENSE.txt
Keywords: Haystack,MCP,Model Context Protocol
Classifier: Development Status :: 4 - Beta
Classifier: License :: OSI Approved :: Apache Software License
Classifier: Programming Language :: Python
Classifier: Programming Language :: Python :: 3.10
Classifier: Programming Language :: Python :: 3.11
Classifier: Programming Language :: Python :: 3.12
Classifier: Programming Language :: Python :: 3.13
Classifier: Programming Language :: Python :: Implementation :: CPython
Requires-Python: >=3.10
Requires-Dist: exceptiongroup
Requires-Dist: haystack-ai>=2.19.0
Requires-Dist: httpx
Requires-Dist: mcp>=1.8.0
